db_helpers/__init__.py
db_helpers/helpers.py
r4s_db_helpers-0.1.1.dist-info/METADATA
r4s_db_helpers-0.1.1.dist-info/WHEEL
r4s_db_helpers-0.1.1.dist-info/RECORD
