Metadata-Version: 2.3
Name: r4s_db_helpers
Version: 0.1.1
Summary: High level classes to communicate with dbs
Author: Artyom rock4ts@gmail.com
Requires-Python: >=3.12
Classifier: Programming Language :: Python :: 3
Classifier: Programming Language :: Python :: 3.12
Classifier: Programming Language :: Python :: 3.13
Requires-Dist: asyncpg (>=0.30.0)
Requires-Dist: pydantic (>=2.10.4)
Requires-Dist: sqlalchemy (>=2.0.41)
